{
  "openapi": "3.0.0",
  "info": {
    "version": "v1.0.0",
    "title": "Project endpoints",
    "description": "Endpoints of project"
  },
  "servers": [
    {
      "url": "http://localhost:5000",
      "description": ""
    }
  ],
  "paths": {
    "/api/user/": {
      "get": {
        "description": "",
        "responses": {
          "default": {
            "description": ""
          }
        }
      },
      "post": {
        "description": "",
        "responses": {
          "default": {
            "description": ""
          }
        }
      }
    },
    "/api/user/{id}": {
      "get": {
        "description": "",
        "responses": {
          "default": {
            "description": ""
          }
        }
      }
    },
    "/api/user/login": {
      "post": {
        "description": "",
        "responses": {
          "default": {
            "description": ""
          }
        }
      }
    },
    "/api/user/logout": {
      "post": {
        "description": "",
        "responses": {
          "default": {
            "description": ""
          }
        }
      }
    }
  },
  "components": {
    "securitySchemes": {
      "bearerAuth": {
        "type": "http",
        "scheme": "bearer"
      }
    }
  }
}